{"dID":86917,"playerDiags":4,"actionNodes":2,"startPoint":0,"loadTag":"","previewPanning":false,"autosave":true,"locEdit":false,"showSettings":true,"pd_isp_0":true,"pd_rect_0":[-360,100],"pd_comSize_0":1,"pd_ID_0":0,"pd_pTag_0":"","pd_sprite_0":"Assets/VIDE/Data/Resources/Sprites/MONSTER POLICE.png","pd_expand_0":false,"pd_vars0":0,"pd_0_com_0iSet":0,"pd_0_com_0oAns":-1,"pd_0_com_0oAct":0,"pd_0_com_0text":"You walk up to the Unicorn-masked guest...","pd_0_com_0extraD":"","pd_0_com_0showmore":false,"pd_0_com_0visible":true,"pd_0_com_0audio":"","pd_0_com_0sprite":"","pd_isp_1":false,"pd_rect_1":[480,-210],"pd_comSize_1":1,"pd_ID_1":21,"pd_pTag_1":"","pd_sprite_1":"","pd_expand_1":false,"pd_vars1":0,"pd_1_com_0iSet":-1,"pd_1_com_0oAns":-1,"pd_1_com_0oAct":1,"pd_1_com_0text":"\"My treasure!!!!!!!!\"","pd_1_com_0extraD":"ExtraData","pd_1_com_0showmore":false,"pd_1_com_0visible":true,"pd_1_com_0audio":"","pd_1_com_0sprite":"","pd_isp_2":true,"pd_rect_2":[570,-450],"pd_comSize_2":1,"pd_ID_2":22,"pd_pTag_2":"","pd_sprite_2":"","pd_expand_2":false,"pd_vars2":0,"pd_2_com_0iSet":-1,"pd_2_com_0oAns":-1,"pd_2_com_0oAct":-1,"pd_2_com_0text":"[Leave]","pd_2_com_0extraD":"ExtraData","pd_2_com_0showmore":false,"pd_2_com_0visible":true,"pd_2_com_0audio":"","pd_2_com_0sprite":"","pd_isp_3":false,"pd_rect_3":[460,0],"pd_comSize_3":1,"pd_ID_3":1,"pd_pTag_3":"","pd_sprite_3":"","pd_expand_3":false,"pd_vars3":0,"pd_3_com_0iSet":-1,"pd_3_com_0oAns":-1,"pd_3_com_0oAct":-1,"pd_3_com_0text":"\"Hello again... I guess.\"","pd_3_com_0extraD":"ExtraData","pd_3_com_0showmore":false,"pd_3_com_0visible":true,"pd_3_com_0audio":"","pd_3_com_0sprite":"","ac_rect_0":[110,10],"ac_ID_0":20,"ac_pause_0":false,"ac_goName_0":"NPC EVENTS","ac_nIndex_0":5,"ac_goto_0":-1,"ac_optsCount_0":6,"ac_opts_0_0":"[No method]","ac_opts_1_0":"Start","ac_opts_2_0":"DestroyObject","ac_opts_3_0":"CameraEvent","ac_opts_4_0":"CheckInHand","ac_opts_5_0":"Update","ac_namesCount_0":10,"ac_names_0_0":"[No object]","ac_names_1_0":"UIMANAGER","ac_names_2_0":"Unicorn","ac_names_3_0":"cm","ac_names_4_0":"PlayerVC","ac_names_5_0":"NPC EVENTS","ac_names_6_0":"Vampire","ac_names_7_0":"DollyTrack1","ac_names_8_0":"GUEST A","ac_names_9_0":"Werewolf","ac_methCount_0":77,"ac_meth_key_0_0":"UIMANAGER0","ac_meth_val_0_0":"CallNext","ac_meth_key_0_1":"Unicorn0","ac_meth_val_0_1":"GetAssigned","ac_meth_key_0_2":"Unicorn1","ac_meth_val_0_2":"AssignNew","ac_meth_key_0_3":"Unicorn2","ac_meth_val_0_3":"SaveState","ac_meth_key_0_4":"Unicorn3","ac_meth_val_0_4":"LoadState","ac_meth_key_0_5":"Unicorn4","ac_meth_val_0_5":"OnBeforeSerialize","ac_meth_key_0_6":"Unicorn5","ac_meth_val_0_6":"OnAfterDeserialize","ac_meth_key_0_7":"Unicorn6","ac_meth_val_0_7":"Start","ac_meth_key_0_8":"Unicorn7","ac_meth_val_0_8":"ChangeColor","ac_meth_key_0_9":"Unicorn8","ac_meth_val_0_9":"Move","ac_meth_key_0_10":"Unicorn9","ac_meth_val_0_10":"GoInvisible","ac_meth_key_0_11":"Unicorn10","ac_meth_val_0_11":"DestroyObject","ac_meth_key_0_12":"cm0","ac_meth_val_0_12":"get_IsValid","ac_meth_key_0_13":"cm1","ac_meth_val_0_13":"get_Stage","ac_meth_key_0_14":"cm2","ac_meth_val_0_14":"get_TrackedPoint","ac_meth_key_0_15":"cm3","ac_meth_val_0_15":"get_HideOffsetInInspector","ac_meth_key_0_16":"cm4","ac_meth_val_0_16":"set_HideOffsetInInspector","ac_meth_key_0_17":"cm5","ac_meth_val_0_17":"get_EffectiveOffset","ac_meth_key_0_18":"cm6","ac_meth_val_0_18":"get_IsValid","ac_meth_key_0_19":"cm7","ac_meth_val_0_19":"get_Stage","ac_meth_key_0_20":"PlayerVC0","ac_meth_val_0_20":"get_State","ac_meth_key_0_21":"PlayerVC1","ac_meth_val_0_21":"get_LookAt","ac_meth_key_0_22":"PlayerVC2","ac_meth_val_0_22":"get_Follow","ac_meth_key_0_23":"PlayerVC3","ac_meth_val_0_23":"InvalidateComponentPipeline","ac_meth_key_0_24":"PlayerVC4","ac_meth_val_0_24":"GetComponentOwner","ac_meth_key_0_25":"PlayerVC5","ac_meth_val_0_25":"GetComponentPipeline","ac_meth_key_0_26":"PlayerVC6","ac_meth_val_0_26":"GetCinemachineComponent","ac_meth_key_0_27":"PlayerVC7","ac_meth_val_0_27":"AddCinemachineComponent","ac_meth_key_0_28":"PlayerVC8","ac_meth_val_0_28":"DestroyCinemachineComponent","ac_meth_key_0_29":"PlayerVC9","ac_meth_val_0_29":"get_UserIsDragging","ac_meth_key_0_30":"PlayerVC10","ac_meth_val_0_30":"set_UserIsDragging","ac_meth_key_0_31":"NPC EVENTS0","ac_meth_val_0_31":"Start","ac_meth_key_0_32":"NPC EVENTS1","ac_meth_val_0_32":"DestroyObject","ac_meth_key_0_33":"NPC EVENTS2","ac_meth_val_0_33":"CameraEvent","ac_meth_key_0_34":"NPC EVENTS3","ac_meth_val_0_34":"CheckInHand","ac_meth_key_0_35":"NPC EVENTS4","ac_meth_val_0_35":"Update","ac_meth_key_0_36":"Vampire0","ac_meth_val_0_36":"Start","ac_meth_key_0_37":"Vampire1","ac_meth_val_0_37":"ChangeColor","ac_meth_key_0_38":"Vampire2","ac_meth_val_0_38":"Move","ac_meth_key_0_39":"Vampire3","ac_meth_val_0_39":"GoInvisible","ac_meth_key_0_40":"Vampire4","ac_meth_val_0_40":"DestroyObject","ac_meth_key_0_41":"Vampire5","ac_meth_val_0_41":"GetAssigned","ac_meth_key_0_42":"Vampire6","ac_meth_val_0_42":"AssignNew","ac_meth_key_0_43":"Vampire7","ac_meth_val_0_43":"SaveState","ac_meth_key_0_44":"Vampire8","ac_meth_val_0_44":"LoadState","ac_meth_key_0_45":"Vampire9","ac_meth_val_0_45":"OnBeforeSerialize","ac_meth_key_0_46":"Vampire10","ac_meth_val_0_46":"OnAfterDeserialize","ac_meth_key_0_47":"DollyTrack10","ac_meth_val_0_47":"get_MinPos","ac_meth_key_0_48":"DollyTrack11","ac_meth_val_0_48":"get_MaxPos","ac_meth_key_0_49":"DollyTrack12","ac_meth_val_0_49":"get_Looped","ac_meth_key_0_50":"DollyTrack13","ac_meth_val_0_50":"get_DistanceCacheSampleStepsPerSegment","ac_meth_key_0_51":"DollyTrack14","ac_meth_val_0_51":"InvalidateDistanceCache","ac_meth_key_0_52":"DollyTrack15","ac_meth_val_0_52":"EvaluatePosition","ac_meth_key_0_53":"DollyTrack16","ac_meth_val_0_53":"EvaluateTangent","ac_meth_key_0_54":"DollyTrack17","ac_meth_val_0_54":"EvaluateOrientation","ac_meth_key_0_55":"GUEST A0","ac_meth_val_0_55":"GetAssigned","ac_meth_key_0_56":"GUEST A1","ac_meth_val_0_56":"AssignNew","ac_meth_key_0_57":"GUEST A2","ac_meth_val_0_57":"SaveState","ac_meth_key_0_58":"GUEST A3","ac_meth_val_0_58":"LoadState","ac_meth_key_0_59":"GUEST A4","ac_meth_val_0_59":"OnBeforeSerialize","ac_meth_key_0_60":"GUEST A5","ac_meth_val_0_60":"OnAfterDeserialize","ac_meth_key_0_61":"GUEST A6","ac_meth_val_0_61":"Start","ac_meth_key_0_62":"GUEST A7","ac_meth_val_0_62":"ChangeColor","ac_meth_key_0_63":"GUEST A8","ac_meth_val_0_63":"Move","ac_meth_key_0_64":"GUEST A9","ac_meth_val_0_64":"GoInvisible","ac_meth_key_0_65":"GUEST A10","ac_meth_val_0_65":"DestroyObject","ac_meth_key_0_66":"Werewolf0","ac_meth_val_0_66":"Start","ac_meth_key_0_67":"Werewolf1","ac_meth_val_0_67":"ChangeColor","ac_meth_key_0_68":"Werewolf2","ac_meth_val_0_68":"Move","ac_meth_key_0_69":"Werewolf3","ac_meth_val_0_69":"GoInvisible","ac_meth_key_0_70":"Werewolf4","ac_meth_val_0_70":"DestroyObject","ac_meth_key_0_71":"Werewolf5","ac_meth_val_0_71":"GetAssigned","ac_meth_key_0_72":"Werewolf6","ac_meth_val_0_72":"AssignNew","ac_meth_key_0_73":"Werewolf7","ac_meth_val_0_73":"SaveState","ac_meth_key_0_74":"Werewolf8","ac_meth_val_0_74":"LoadState","ac_meth_key_0_75":"Werewolf9","ac_meth_val_0_75":"OnBeforeSerialize","ac_meth_key_0_76":"Werewolf10","ac_meth_val_0_76":"OnAfterDeserialize","ac_meth_0":"CheckInHand","ac_paramT_0":0,"ac_methIndex_0":4,"ac_pString_0":null,"ac_pBool_0":false,"ac_pInt_0":0,"ac_pFloat_0":0,"ac_oSet_0":-1,"ac_oAct_0":-1,"ac_ovrStartNode_0":-1,"ac_renameDialogue_0":"","ac_more_0":false,"ac_rect_1":[950,-280],"ac_ID_1":2,"ac_pause_1":false,"ac_goName_1":"NPC EVENTS","ac_nIndex_1":10,"ac_goto_1":-1,"ac_optsCount_1":16,"ac_opts_0_1":"[No method]","ac_opts_1_1":"Start","ac_opts_2_1":"OnGUI","ac_opts_3_1":"DestroyObject","ac_opts_4_1":"CameraEventWerewolf","ac_opts_5_1":"CameraEventVampire","ac_opts_6_1":"CameraEventDragon","ac_opts_7_1":"CheckInHand","ac_opts_8_1":"AddChaos","ac_opts_9_1":"Update","ac_opts_10_1":"GetAssigned","ac_opts_11_1":"AssignNew","ac_opts_12_1":"SaveState","ac_opts_13_1":"LoadState","ac_opts_14_1":"OnBeforeSerialize","ac_opts_15_1":"OnAfterDeserialize","ac_namesCount_1":14,"ac_names_0_1":"[No object]","ac_names_1_1":"DollyTrack3","ac_names_2_1":"DollyTrack2","ac_names_3_1":"UIMANAGER","ac_names_4_1":"DollyTrack1","ac_names_5_1":"Unicorn","ac_names_6_1":"Ghost","ac_names_7_1":"cm","ac_names_8_1":"Dragon","ac_names_9_1":"PlayerVC","ac_names_10_1":"NPC EVENTS","ac_names_11_1":"Vampire","ac_names_12_1":"Witch","ac_names_13_1":"Werewolf","ac_methCount_1":125,"ac_meth_key_1_0":"DollyTrack30","ac_meth_val_1_0":"get_MinPos","ac_meth_key_1_1":"DollyTrack31","ac_meth_val_1_1":"get_MaxPos","ac_meth_key_1_2":"DollyTrack32","ac_meth_val_1_2":"get_Looped","ac_meth_key_1_3":"DollyTrack33","ac_meth_val_1_3":"get_DistanceCacheSampleStepsPerSegment","ac_meth_key_1_4":"DollyTrack34","ac_meth_val_1_4":"InvalidateDistanceCache","ac_meth_key_1_5":"DollyTrack35","ac_meth_val_1_5":"EvaluatePosition","ac_meth_key_1_6":"DollyTrack36","ac_meth_val_1_6":"EvaluateTangent","ac_meth_key_1_7":"DollyTrack37","ac_meth_val_1_7":"EvaluateOrientation","ac_meth_key_1_8":"DollyTrack20","ac_meth_val_1_8":"get_MinPos","ac_meth_key_1_9":"DollyTrack21","ac_meth_val_1_9":"get_MaxPos","ac_meth_key_1_10":"DollyTrack22","ac_meth_val_1_10":"get_Looped","ac_meth_key_1_11":"DollyTrack23","ac_meth_val_1_11":"get_DistanceCacheSampleStepsPerSegment","ac_meth_key_1_12":"DollyTrack24","ac_meth_val_1_12":"InvalidateDistanceCache","ac_meth_key_1_13":"DollyTrack25","ac_meth_val_1_13":"EvaluatePosition","ac_meth_key_1_14":"DollyTrack26","ac_meth_val_1_14":"EvaluateTangent","ac_meth_key_1_15":"DollyTrack27","ac_meth_val_1_15":"EvaluateOrientation","ac_meth_key_1_16":"UIMANAGER0","ac_meth_val_1_16":"CallNext","ac_meth_key_1_17":"DollyTrack10","ac_meth_val_1_17":"get_MinPos","ac_meth_key_1_18":"DollyTrack11","ac_meth_val_1_18":"get_MaxPos","ac_meth_key_1_19":"DollyTrack12","ac_meth_val_1_19":"get_Looped","ac_meth_key_1_20":"DollyTrack13","ac_meth_val_1_20":"get_DistanceCacheSampleStepsPerSegment","ac_meth_key_1_21":"DollyTrack14","ac_meth_val_1_21":"InvalidateDistanceCache","ac_meth_key_1_22":"DollyTrack15","ac_meth_val_1_22":"EvaluatePosition","ac_meth_key_1_23":"DollyTrack16","ac_meth_val_1_23":"EvaluateTangent","ac_meth_key_1_24":"DollyTrack17","ac_meth_val_1_24":"EvaluateOrientation","ac_meth_key_1_25":"Unicorn0","ac_meth_val_1_25":"GetAssigned","ac_meth_key_1_26":"Unicorn1","ac_meth_val_1_26":"AssignNew","ac_meth_key_1_27":"Unicorn2","ac_meth_val_1_27":"SaveState","ac_meth_key_1_28":"Unicorn3","ac_meth_val_1_28":"LoadState","ac_meth_key_1_29":"Unicorn4","ac_meth_val_1_29":"OnBeforeSerialize","ac_meth_key_1_30":"Unicorn5","ac_meth_val_1_30":"OnAfterDeserialize","ac_meth_key_1_31":"Unicorn6","ac_meth_val_1_31":"Start","ac_meth_key_1_32":"Unicorn7","ac_meth_val_1_32":"ChangeColor","ac_meth_key_1_33":"Unicorn8","ac_meth_val_1_33":"Move","ac_meth_key_1_34":"Unicorn9","ac_meth_val_1_34":"GoInvisible","ac_meth_key_1_35":"Unicorn10","ac_meth_val_1_35":"DestroyObject","ac_meth_key_1_36":"Ghost0","ac_meth_val_1_36":"Start","ac_meth_key_1_37":"Ghost1","ac_meth_val_1_37":"ChangeColor","ac_meth_key_1_38":"Ghost2","ac_meth_val_1_38":"Move","ac_meth_key_1_39":"Ghost3","ac_meth_val_1_39":"GoInvisible","ac_meth_key_1_40":"Ghost4","ac_meth_val_1_40":"DestroyObject","ac_meth_key_1_41":"Ghost5","ac_meth_val_1_41":"GetAssigned","ac_meth_key_1_42":"Ghost6","ac_meth_val_1_42":"AssignNew","ac_meth_key_1_43":"Ghost7","ac_meth_val_1_43":"SaveState","ac_meth_key_1_44":"Ghost8","ac_meth_val_1_44":"LoadState","ac_meth_key_1_45":"Ghost9","ac_meth_val_1_45":"OnBeforeSerialize","ac_meth_key_1_46":"Ghost10","ac_meth_val_1_46":"OnAfterDeserialize","ac_meth_key_1_47":"cm0","ac_meth_val_1_47":"get_IsValid","ac_meth_key_1_48":"cm1","ac_meth_val_1_48":"get_Stage","ac_meth_key_1_49":"cm2","ac_meth_val_1_49":"get_TrackedPoint","ac_meth_key_1_50":"cm3","ac_meth_val_1_50":"get_HideOffsetInInspector","ac_meth_key_1_51":"cm4","ac_meth_val_1_51":"set_HideOffsetInInspector","ac_meth_key_1_52":"cm5","ac_meth_val_1_52":"get_EffectiveOffset","ac_meth_key_1_53":"cm6","ac_meth_val_1_53":"get_IsValid","ac_meth_key_1_54":"cm7","ac_meth_val_1_54":"get_Stage","ac_meth_key_1_55":"Dragon0","ac_meth_val_1_55":"GetAssigned","ac_meth_key_1_56":"Dragon1","ac_meth_val_1_56":"AssignNew","ac_meth_key_1_57":"Dragon2","ac_meth_val_1_57":"SaveState","ac_meth_key_1_58":"Dragon3","ac_meth_val_1_58":"LoadState","ac_meth_key_1_59":"Dragon4","ac_meth_val_1_59":"OnBeforeSerialize","ac_meth_key_1_60":"Dragon5","ac_meth_val_1_60":"OnAfterDeserialize","ac_meth_key_1_61":"Dragon6","ac_meth_val_1_61":"Start","ac_meth_key_1_62":"Dragon7","ac_meth_val_1_62":"ChangeColor","ac_meth_key_1_63":"Dragon8","ac_meth_val_1_63":"Move","ac_meth_key_1_64":"Dragon9","ac_meth_val_1_64":"GoInvisible","ac_meth_key_1_65":"Dragon10","ac_meth_val_1_65":"DestroyObject","ac_meth_key_1_66":"PlayerVC0","ac_meth_val_1_66":"get_State","ac_meth_key_1_67":"PlayerVC1","ac_meth_val_1_67":"get_LookAt","ac_meth_key_1_68":"PlayerVC2","ac_meth_val_1_68":"get_Follow","ac_meth_key_1_69":"PlayerVC3","ac_meth_val_1_69":"InvalidateComponentPipeline","ac_meth_key_1_70":"PlayerVC4","ac_meth_val_1_70":"GetComponentOwner","ac_meth_key_1_71":"PlayerVC5","ac_meth_val_1_71":"GetComponentPipeline","ac_meth_key_1_72":"PlayerVC6","ac_meth_val_1_72":"GetCinemachineComponent","ac_meth_key_1_73":"PlayerVC7","ac_meth_val_1_73":"AddCinemachineComponent","ac_meth_key_1_74":"PlayerVC8","ac_meth_val_1_74":"DestroyCinemachineComponent","ac_meth_key_1_75":"PlayerVC9","ac_meth_val_1_75":"get_UserIsDragging","ac_meth_key_1_76":"PlayerVC10","ac_meth_val_1_76":"set_UserIsDragging","ac_meth_key_1_77":"NPC EVENTS0","ac_meth_val_1_77":"Start","ac_meth_key_1_78":"NPC EVENTS1","ac_meth_val_1_78":"OnGUI","ac_meth_key_1_79":"NPC EVENTS2","ac_meth_val_1_79":"DestroyObject","ac_meth_key_1_80":"NPC EVENTS3","ac_meth_val_1_80":"CameraEventWerewolf","ac_meth_key_1_81":"NPC EVENTS4","ac_meth_val_1_81":"CameraEventVampire","ac_meth_key_1_82":"NPC EVENTS5","ac_meth_val_1_82":"CameraEventDragon","ac_meth_key_1_83":"NPC EVENTS6","ac_meth_val_1_83":"CheckInHand","ac_meth_key_1_84":"NPC EVENTS7","ac_meth_val_1_84":"AddChaos","ac_meth_key_1_85":"NPC EVENTS8","ac_meth_val_1_85":"Update","ac_meth_key_1_86":"NPC EVENTS9","ac_meth_val_1_86":"GetAssigned","ac_meth_key_1_87":"NPC EVENTS10","ac_meth_val_1_87":"AssignNew","ac_meth_key_1_88":"NPC EVENTS11","ac_meth_val_1_88":"SaveState","ac_meth_key_1_89":"NPC EVENTS12","ac_meth_val_1_89":"LoadState","ac_meth_key_1_90":"NPC EVENTS13","ac_meth_val_1_90":"OnBeforeSerialize","ac_meth_key_1_91":"NPC EVENTS14","ac_meth_val_1_91":"OnAfterDeserialize","ac_meth_key_1_92":"Vampire0","ac_meth_val_1_92":"Start","ac_meth_key_1_93":"Vampire1","ac_meth_val_1_93":"ChangeColor","ac_meth_key_1_94":"Vampire2","ac_meth_val_1_94":"Move","ac_meth_key_1_95":"Vampire3","ac_meth_val_1_95":"GoInvisible","ac_meth_key_1_96":"Vampire4","ac_meth_val_1_96":"DestroyObject","ac_meth_key_1_97":"Vampire5","ac_meth_val_1_97":"GetAssigned","ac_meth_key_1_98":"Vampire6","ac_meth_val_1_98":"AssignNew","ac_meth_key_1_99":"Vampire7","ac_meth_val_1_99":"SaveState","ac_meth_key_1_100":"Vampire8","ac_meth_val_1_100":"LoadState","ac_meth_key_1_101":"Vampire9","ac_meth_val_1_101":"OnBeforeSerialize","ac_meth_key_1_102":"Vampire10","ac_meth_val_1_102":"OnAfterDeserialize","ac_meth_key_1_103":"Witch0","ac_meth_val_1_103":"GetAssigned","ac_meth_key_1_104":"Witch1","ac_meth_val_1_104":"AssignNew","ac_meth_key_1_105":"Witch2","ac_meth_val_1_105":"SaveState","ac_meth_key_1_106":"Witch3","ac_meth_val_1_106":"LoadState","ac_meth_key_1_107":"Witch4","ac_meth_val_1_107":"OnBeforeSerialize","ac_meth_key_1_108":"Witch5","ac_meth_val_1_108":"OnAfterDeserialize","ac_meth_key_1_109":"Witch6","ac_meth_val_1_109":"Start","ac_meth_key_1_110":"Witch7","ac_meth_val_1_110":"ChangeColor","ac_meth_key_1_111":"Witch8","ac_meth_val_1_111":"Move","ac_meth_key_1_112":"Witch9","ac_meth_val_1_112":"GoInvisible","ac_meth_key_1_113":"Witch10","ac_meth_val_1_113":"DestroyObject","ac_meth_key_1_114":"Werewolf0","ac_meth_val_1_114":"Start","ac_meth_key_1_115":"Werewolf1","ac_meth_val_1_115":"ChangeColor","ac_meth_key_1_116":"Werewolf2","ac_meth_val_1_116":"Move","ac_meth_key_1_117":"Werewolf3","ac_meth_val_1_117":"GoInvisible","ac_meth_key_1_118":"Werewolf4","ac_meth_val_1_118":"DestroyObject","ac_meth_key_1_119":"Werewolf5","ac_meth_val_1_119":"GetAssigned","ac_meth_key_1_120":"Werewolf6","ac_meth_val_1_120":"AssignNew","ac_meth_key_1_121":"Werewolf7","ac_meth_val_1_121":"SaveState","ac_meth_key_1_122":"Werewolf8","ac_meth_val_1_122":"LoadState","ac_meth_key_1_123":"Werewolf9","ac_meth_val_1_123":"OnBeforeSerialize","ac_meth_key_1_124":"Werewolf10","ac_meth_val_1_124":"OnAfterDeserialize","ac_meth_1":"CameraEventDragon","ac_paramT_1":0,"ac_methIndex_1":6,"ac_pString_1":null,"ac_pBool_1":false,"ac_pInt_1":0,"ac_pFloat_1":0,"ac_oSet_1":-1,"ac_oAct_1":-1,"ac_ovrStartNode_1":-1,"ac_renameDialogue_1":"","ac_more_1":false}